slack_backup/__init__.py
slack_backup/client.py
slack_backup/command.py
slack_backup/config.py
slack_backup/db.py
slack_backup/download.py
slack_backup/emoji.py
slack_backup/objects.py
slack_backup/reporters.py
slack_backup/utils.py
slack_backup-0.8.data/scripts/slack-backup
slack_backup-0.8.dist-info/LICENSE
slack_backup-0.8.dist-info/METADATA
slack_backup-0.8.dist-info/WHEEL
slack_backup-0.8.dist-info/top_level.txt
slack_backup-0.8.dist-info/RECORD
