Metadata-Version: 2.1
Name: slack-backup
Version: 0.8
Summary: Make copy of slack converstaions
Home-page: https://github.com/gryf/slack-backup
Author: Roman Dobosz
Author-email: gryf73@gmail.com
License: UNKNOWN
Download-URL: https://github.com/gryf/slack-backup
Keywords: chat,backup,history,slack
Platform: UNKNOWN
Classifier: Programming Language :: Python :: 3
Classifier: Programming Language :: Python :: 3.4
Classifier: Development Status :: 4 - Beta
Classifier: Environment :: Console
Classifier: Intended Audience :: End Users/Desktop
Classifier: License :: OSI Approved :: BSD License
Classifier: Operating System :: OS Independent
Classifier: Topic :: Internet :: WWW/HTTP
Classifier: Topic :: Database :: Front-Ends
Classifier: Topic :: Communications :: Chat
Classifier: Topic :: Text Processing :: Markup
Classifier: Topic :: Text Processing :: Markup :: HTML
Requires-Dist: sqlalchemy
Requires-Dist: slackclient
